CONTRIBUTING.rst
LICENSE
MANIFEST.in
README.rst
setup.cfg
setup.py
docs/Makefile
docs/api.rst
docs/conf.py
docs/contributing.rst
docs/dataset.rst
docs/estimator.rst
docs/feature.rst
docs/heamy.rst
docs/heamy.utils.rst
docs/index.rst
docs/installation.rst
docs/make.bat
docs/pipeline.rst
docs/readme.rst
docs/usage.rst
docs/_build/html/_static/ajax-loader.gif
docs/_build/html/_static/background_b01.png
docs/_build/html/_static/bgfooter.png
docs/_build/html/_static/bgtop.png
docs/_build/html/_static/comment-bright.png
docs/_build/html/_static/comment-close.png
docs/_build/html/_static/comment.png
docs/_build/html/_static/down-pressed.png
docs/_build/html/_static/down.png
docs/_build/html/_static/file.png
docs/_build/html/_static/minus.png
docs/_build/html/_static/plus.png
docs/_build/html/_static/up-pressed.png
docs/_build/html/_static/up.png
heamy/__init__.py
heamy/cache.py
heamy/dataset.py
heamy/estimator.py
heamy/feature.py
heamy/pipeline.py
heamy.egg-info/PKG-INFO
heamy.egg-info/SOURCES.txt
heamy.egg-info/dependency_links.txt
heamy.egg-info/not-zip-safe
heamy.egg-info/requires.txt
heamy.egg-info/top_level.txt
heamy/utils/__init__.py
heamy/utils/main.py
heamy/utils/optimizer.py
tests/test_dataset.py
tests/test_estimator.py
tests/test_feature.py
tests/test_helpers.py
tests/test_pipeline.py