Metadata-Version: 1.1
Name: heamy
Version: 0.0.7
Summary: A set of useful tools for competitive data science.
Home-page: https://github.com/rushter/heamy
Author: Artem Golubin
Author-email: me@rushter.com
License: MIT
Keywords: heamy
Platform: UNKNOWN
Classifier: Development Status :: 2 - Pre-Alpha
Classifier: Intended Audience :: Developers
Classifier: License :: OSI Approved :: MIT License
Classifier: Natural Language :: English
Classifier: Programming Language :: Python :: 2
Classifier: Programming Language :: Python :: 2.6
Classifier: Programming Language :: Python :: 2.7
Classifier: Programming Language :: Python :: 3
Classifier: Programming Language :: Python :: 3.3
Classifier: Programming Language :: Python :: 3.4
Classifier: Programming Language :: Python :: 3.5
